stapidoc/__init__.py
stapidoc/__main__.py
stapidoc/stapi.py
stapidoc/stapidoc.mako
stapidoc-0.1.0.dist-info/METADATA
stapidoc-0.1.0.dist-info/WHEEL
stapidoc-0.1.0.dist-info/entry_points.txt
stapidoc-0.1.0.dist-info/top_level.txt
stapidoc-0.1.0.dist-info/RECORD
