Metadata-Version: 2.1
Name: stapidoc
Version: 0.1.0
Summary: Static Page Inline Decoder of Choice
Author-email: Jonas Santoso <santojo@pm.me>
Project-URL: Homepage, https://github.com/santosoj/stapidoc
Requires-Python: >=3.10
Requires-Dist: beautifulsoup4 ~=4.12
Requires-Dist: html5lib ~=1.1
Requires-Dist: Mako ~=1.2
